<metadata xml:lang="en"><Esri><CreaDate>20111115</CreaDate><CreaTime>16234600</CreaTime><ArcGISFormat>1.0</ArcGISFormat><ArcGISstyle>ISO 19139 Metadata Implementation Specification</ArcGISstyle><SyncOnce>FALSE</SyncOnce><ArcGISProfile>ISO19139</ArcGISProfile><DataProperties><lineage><Process export="False" Name="" ToolSource=""/></lineage><itemProps><itemLocation><linkage Sync="TRUE">file://\\ICF2002222\H$\GIS\08_GPS\04_Completed_Surveys\Kenya\Kenya_2003_DHS\audit_Kenya_2003_DHS\Review_File\KEGE43FL.shp</linkage><protocol Sync="TRUE">Local Area Network</protocol></itemLocation><itemName Sync="TRUE">KEGE43FL</itemName><imsContentType Sync="TRUE">002</imsContentType><nativeExtBox><westBL Sync="TRUE">0.000000</westBL><eastBL Sync="TRUE">41.883772</eastBL><southBL Sync="TRUE">-4.664255</southBL><northBL Sync="TRUE">4.243911</northBL><exTypeCode Sync="TRUE">1</exTypeCode></nativeExtBox><itemSize Sync="TRUE">0.011</itemSize></itemProps><copyHistory><copy source="H:\GIS\08_GPS\01_Template\GPS_Metadata_Template" dest="\\ICF2011990\H$\GIS\08_GPS\01_Template\GPS_Metadata_Template" date="20111115" time="16234600"/></copyHistory><coordRef><type Sync="TRUE">Geographic</type><geogcsn Sync="TRUE">GCS_WGS_1984</geogcsn><csUnits Sync="TRUE">Angular Unit: Degree (0.017453)</csUnits><peXml Sync="TRUE">&lt;GeographicCoordinateSystem xsi:type='typens:GeographicCoordinateSystem' xmlns:xsi='http://www.w3.org/2001/XMLSchema-instance' xmlns:xs='http://www.w3.org/2001/XMLSchema' xmlns:typens='http://www.esri.com/schemas/ArcGIS/10.0'&gt;&lt;WKT&gt;GEOGCS[&amp;quot;GCS_WGS_1984&amp;quot;,DATUM[&amp;quot;D_WGS_1984&amp;quot;,SPHEROID[&amp;quot;WGS_1984&amp;quot;,6378137.0,298.257223563]],PRIMEM[&amp;quot;Greenwich&amp;quot;,0.0],UNIT[&amp;quot;Degree&amp;quot;,0.0174532925199433]]&lt;/WKT&gt;&lt;XOrigin&gt;-399.99999999999989&lt;/XOrigin&gt;&lt;YOrigin&gt;-399.99999999999989&lt;/YOrigin&gt;&lt;XYScale&gt;11258999068426.24&lt;/XYScale&gt;&lt;ZOrigin&gt;-100000&lt;/ZOrigin&gt;&lt;ZScale&gt;10000&lt;/ZScale&gt;&lt;MOrigin&gt;-100000&lt;/MOrigin&gt;&lt;MScale&gt;10000&lt;/MScale&gt;&lt;XYTolerance&gt;8.9831528411952133e-009&lt;/XYTolerance&gt;&lt;ZTolerance&gt;0.001&lt;/ZTolerance&gt;&lt;MTolerance&gt;0.001&lt;/MTolerance&gt;&lt;HighPrecision&gt;true&lt;/HighPrecision&gt;&lt;LeftLongitude&gt;-180&lt;/LeftLongitude&gt;&lt;WKID&gt;4326&lt;/WKID&gt;&lt;/GeographicCoordinateSystem&gt;</peXml></coordRef></DataProperties><ModDate>20120213</ModDate><ModTime>13431900</ModTime><SyncDate>20120213</SyncDate><SyncTime>13431900</SyncTime></Esri><dataIdInfo><idPurp>This shapefile provides the geographic information of the surveyed clusters.</idPurp><idAbs>&lt;DIV STYLE="text-align:Left;"&gt;&lt;DIV&gt;&lt;DIV&gt;&lt;P&gt;&lt;SPAN&gt;&lt;SPAN&gt;The geographic datafile contains the DHS cluster ID, DHS country code, FIPS country code, FIPS region name and code (if applicable), SALB region name and code (if applicable), DHS region name and code, source type (e.g. GPS, MIS, CEN, GAZ), urban or rural classification (i.e. U or R), latitude and longitude coordinates in decimal degrees, altitude in meters from either the GPS receiver and/or a digital elevation model (DEM), and the geographic datum (i.e. WGS84).&lt;/SPAN&gt;&lt;/SPAN&gt;&lt;/P&gt;&lt;/DIV&gt;&lt;/DIV&gt;&lt;/DIV&gt;</idAbs><idCredit>Implementing Organization, Kenya Central Bureau of Statistics (CBS) and ICF International Calverton, Maryland, USA</idCredit><idCitation xmlns=""><resTitle>Kenya 2003 DHS</resTitle><resAltTitle>KEGE43FL</resAltTitle><presForm xmlns=""><PresFormCd value="005"/></presForm><citRespParty xmlns=""><rpIndName>GIS Analyst</rpIndName><rpOrgName>ICF International</rpOrgName><rpPosName>GIS Analyst</rpPosName><rpCntInfo xmlns=""><cntAddress addressType=""><delPoint>11785 Beltsville Drive, Suite 400</delPoint><city>Calverton</city><adminArea>MD</adminArea><postCode>20705</postCode><eMailAdd>gpsrequests@measuredhs.com</eMailAdd><country>USA</country></cntAddress><cntPhone><voiceNum tddtty="">301.572.0200</voiceNum><faxNum>301.572.0999</faxNum></cntPhone><cntHours>9:00a – 5:00p EST</cntHours><cntOnlineRes xmlns=""><linkage>www.measuredhs.com</linkage></cntOnlineRes></rpCntInfo><role><RoleCd value="005"/></role></citRespParty><citId xmlns=""><identCode>KEGE43FL</identCode><identAuth xmlns=""><citId xmlns=""><identCode>KEGE43FL</identCode><identAuth xmlns=""><citId xmlns=""><identCode>KEGE43FL</identCode></citId></identAuth></citId></identAuth></citId></idCitation><searchKeys><keyword>Demographic and Health Survey</keyword><keyword>DHS</keyword><keyword>Global Positioning System</keyword><keyword>GPS</keyword></searchKeys><resConst xmlns=""><Consts xmlns=""><useLimit>Datasets are made available with the following conditions:

1) Survey data files are distributed by MEASURE DHS for academic research/statistical analysis. Researchers need to provide a description of any research/analysis that will be using the data, before access is granted to the datasets.

2) Once downloaded, the datasets must not be passed on to other researchers without the written consent of MEASURE DHS.

3) All reports and publications based on the requested data must be sent to the MEASURE DHS Data Archive as a Portable Format Document (pdf) or a hard copy, for us to forward to the country(ies) whose data have been used.</useLimit></Consts></resConst><dataChar><CharSetCd value="004"/></dataChar><idPoC xmlns=""><rpIndName>GIS Analyst</rpIndName><rpOrgName>ICF International</rpOrgName><rpPosName>GIS Analyst</rpPosName><rpCntInfo xmlns=""><cntAddress addressType=""><delPoint>11785 Beltsville Drive, Suite 400</delPoint><city>Calverton</city><adminArea>MD</adminArea><postCode>20705</postCode><eMailAdd>gpsrequests@measuredhs.com</eMailAdd><country>USA</country></cntAddress><cntPhone><voiceNum tddtty="">301.572.0200</voiceNum><faxNum>301.572.0999</faxNum></cntPhone><cntHours>9:00a – 5:00p EST</cntHours><cntOnlineRes xmlns=""><linkage>www.measuredhs.com</linkage></cntOnlineRes></rpCntInfo><role><RoleCd value="005"/></role></idPoC><resMaint xmlns=""><maintFreq><MaintFreqCd value="011"/></maintFreq><maintScp><ScopeCd value="009"/></maintScp></resMaint><envirDesc Sync="TRUE">Microsoft Windows 7 Version 6.1 (Build 7601) Service Pack 1; ESRI ArcGIS 10.0.3.3600</envirDesc><dataLang><languageCode value="eng" Sync="TRUE"/><countryCode value="USA" Sync="TRUE"/></dataLang><spatRpType><SpatRepTypCd value="001" Sync="TRUE"/></spatRpType><dataExt><geoEle><GeoBndBox esriExtentType="search"><exTypeCode Sync="TRUE">1</exTypeCode><westBL Sync="TRUE">0.000000</westBL><eastBL Sync="TRUE">41.883772</eastBL><northBL Sync="TRUE">4.243911</northBL><southBL Sync="TRUE">-4.664255</southBL></GeoBndBox></geoEle></dataExt><tpCat><TopicCatCd value="009"/></tpCat><tpCat><TopicCatCd value="013"/></tpCat></dataIdInfo><mdFileID>KEGE43FL</mdFileID><mdChar><CharSetCd value="004"/></mdChar><dataSetURI>http://www.measuredhs.com/data/dataset/Kenya_Standard-DHS_2003.cfm</dataSetURI><mdContact xmlns=""><rpIndName>GIS Analyst</rpIndName><rpOrgName>ICF International</rpOrgName><rpPosName>GIS Analyst</rpPosName><rpCntInfo xmlns=""><cntAddress addressType=""><delPoint>11785 Beltsville Drive, Suite 400</delPoint><city>Calverton</city><adminArea>MD</adminArea><postCode>20705</postCode><eMailAdd>gpsrequests@measuredhs.com</eMailAdd><country>USA</country></cntAddress><cntPhone><voiceNum tddtty="">301.572.0200</voiceNum><faxNum>301.572.0999</faxNum></cntPhone><cntHours>9:00a – 5:00p EST</cntHours><cntOnlineRes xmlns=""><linkage>www.measuredhs.com</linkage></cntOnlineRes></rpCntInfo><role><RoleCd value="005"/></role></mdContact><mdConst xmlns=""><Consts xmlns=""><useLimit>Datasets are made available with the following conditions:

1. Survey data files are distributed by MEASURE DHS for academic research/statistical analysis. Researchers need to provide a description of any research/analysis that will be using the data, before access is granted to the datasets.

2. Once downloaded, the datasets must not be passed on to other researchers without the written consent of MEASURE DHS.

3. All reports and publications based on the requested data must be sent to the MEASURE DHS Data Archive as a Portable Format Document (pdf) or a hard copy, for us to forward to the country(ies) whose data have been used.</useLimit></Consts></mdConst><eainfo><detailed xmlns="" Name="KEGE43FL"><enttyp><enttypl>KEGE43FL</enttypl><enttypt>Shapefile</enttypt><enttypc Sync="TRUE">400</enttypc></enttyp><attr xmlns=""><attrlabl Sync="TRUE">FID</attrlabl><attalias Sync="TRUE">FID</attalias><attrtype Sync="TRUE">OID</attrtype><attwidth Sync="TRUE">4</attwidth><atprecis Sync="TRUE">0</atprecis><attscale Sync="TRUE">0</attscale><attrdef Sync="TRUE">Internal feature number.</attrdef><attrdefs Sync="TRUE">ESRI</attrdefs><attrdomv><udom Sync="TRUE">Sequential unique whole numbers that are automatically generated.</udom></attrdomv></attr><attr xmlns=""><attrlabl Sync="TRUE">Shape</attrlabl><attalias Sync="TRUE">Shape</attalias><attrtype Sync="TRUE">Geometry</attrtype><attwidth Sync="TRUE">0</attwidth><atprecis Sync="TRUE">0</atprecis><attscale Sync="TRUE">0</attscale><attrdef Sync="TRUE">Feature geometry.</attrdef><attrdefs Sync="TRUE">ESRI</attrdefs><attrdomv><udom Sync="TRUE">Coordinates defining the features.</udom></attrdomv></attr><attr xmlns=""><attrlabl>DHSID</attrlabl><attalias>DHS Unique Identification</attalias><attrdef>14 character DHS identification code - DHSCC &amp; DHSYEAR &amp; DHSCLUST (with 8 digits)</attrdef><attrdefs>survey documentation</attrdefs><attrtype Sync="TRUE">String</attrtype><attwidth Sync="TRUE">254</attwidth><atprecis Sync="TRUE">0</atprecis><attscale Sync="TRUE">0</attscale></attr><attr xmlns=""><attrlabl>DHSCC</attrlabl><attalias>DHS Country Code</attalias><attrdef>2 letter DHS country code</attrdef><attrdefs>http://www.measuredhs.com/data/File-Types-and-Names.cfm</attrdefs><attrtype Sync="TRUE">String</attrtype><attwidth Sync="TRUE">254</attwidth><atprecis Sync="TRUE">0</atprecis><attscale Sync="TRUE">0</attscale></attr><attr xmlns=""><attrlabl>DHSYEAR</attrlabl><attalias>DHS Survey Year</attalias><attrdef>4 digit year of data collection </attrdef><attrdefs>survey documentation</attrdefs><attrtype Sync="TRUE">Double</attrtype><attwidth Sync="TRUE">19</attwidth><atprecis Sync="TRUE">0</atprecis><attscale Sync="TRUE">0</attscale></attr><attr xmlns=""><attrlabl>DHSCLUST</attrlabl><attalias>DHS Cluster Number</attalias><attrdef>integer cluster identification number, this variable will match v001 in the DHS recode file</attrdef><attrdefs>survey documentation</attrdefs><attrtype Sync="TRUE">Double</attrtype><attwidth Sync="TRUE">19</attwidth><atprecis Sync="TRUE">0</atprecis><attscale Sync="TRUE">0</attscale></attr><attr xmlns=""><attrlabl>CCFIPS</attrlabl><attalias>FIPS Country Code</attalias><attrdef>Federal Information Processing Standards (FIPS) 2 letter country code</attrdef><attrdefs>http://www.itl.nist.gov/fipspubs/fip10-4.htm </attrdefs><attrtype Sync="TRUE">String</attrtype><attwidth Sync="TRUE">254</attwidth><atprecis Sync="TRUE">0</atprecis><attscale Sync="TRUE">0</attscale></attr><attr xmlns=""><attrlabl>ADM1FIPS</attrlabl><attalias>FIPS Administrative Level 1 Code</attalias><attrdef>Federal Information Processing Standards (FIPS) 2  letter country code plus 2 letter/digit first sub-national administrative division code; if this information is not available, this field will be "NULL"</attrdef><attrdefs>http://www.itl.nist.gov/fipspubs/fip10-4.htm </attrdefs><attrtype Sync="TRUE">String</attrtype><attwidth Sync="TRUE">254</attwidth><atprecis Sync="TRUE">0</atprecis><attscale Sync="TRUE">0</attscale></attr><attr xmlns=""><attrlabl>ADM1FIPSNA</attrlabl><attalias>FIPS Administrative Level 1 Name</attalias><attrdef>Federal Information Processing Standards (FIPS) first sub-national administrative division name; if this information is not available, this field will be "NULL"</attrdef><attrdefs>http://www.itl.nist.gov/fipspubs/fip10-4.htm </attrdefs><attrtype Sync="TRUE">String</attrtype><attwidth Sync="TRUE">254</attwidth><atprecis Sync="TRUE">0</atprecis><attscale Sync="TRUE">0</attscale></attr><attr xmlns=""><attrlabl>ADM1SALBNA</attrlabl><attalias>SALB Administrative Level 1 Name</attalias><attrdef>Second Administrative Level Boundaries (SALB) first sub-national administrative division name; if this information is not available, this field will be "NULL"</attrdef><attrdefs>http://www.unsalb.org </attrdefs><attrtype Sync="TRUE">String</attrtype><attwidth Sync="TRUE">254</attwidth><atprecis Sync="TRUE">0</atprecis><attscale Sync="TRUE">0</attscale></attr><attr xmlns=""><attrlabl>ADM1SALBCO</attrlabl><attalias>SALB Administrative Level 1 Code</attalias><attrdef>Second Administrative Level Boundaries (SALB) first sub-national administrative division code; if this information is not available, this field will be "NULL"</attrdef><attrdefs>http://www.unsalb.org </attrdefs><attrtype Sync="TRUE">String</attrtype><attwidth Sync="TRUE">254</attwidth><atprecis Sync="TRUE">0</atprecis><attscale Sync="TRUE">0</attscale></attr><attr xmlns=""><attrlabl>ADM1DHS</attrlabl><attalias>Administrative Level 1 Code</attalias><attrdef>First sub-national administrative division code when the DHS sample is representative at the admin 1 level, this variable will usually match v024 in the DHS recode file; if this information is not available, this field will be "9999"</attrdef><attrdefs>survey documentation</attrdefs><attrtype Sync="TRUE">Double</attrtype><attwidth Sync="TRUE">19</attwidth><atprecis Sync="TRUE">0</atprecis><attscale Sync="TRUE">0</attscale></attr><attr xmlns=""><attrlabl>ADM1NAME</attrlabl><attalias>Administrative Level 1 Name</attalias><attrdef>First sub-national administrative division name when the DHS sample is representative at the admin 1 level, this variable will usually match v024 in the DHS recode file; if this information is not available, this field will be "NULL"</attrdef><attrdefs>survey documentation</attrdefs><attrtype Sync="TRUE">String</attrtype><attwidth Sync="TRUE">254</attwidth><atprecis Sync="TRUE">0</atprecis><attscale Sync="TRUE">0</attscale></attr><attr xmlns=""><attrlabl>DHSREGCO</attrlabl><attalias>DHS Region Code</attalias><attrdef>integer region code associated with the DHS region created for sampling, this variable will match either v024 or the country specific region variable in the DHS recode file</attrdef><attrdefs>survey documentation</attrdefs><attrtype Sync="TRUE">Double</attrtype><attwidth Sync="TRUE">19</attwidth><atprecis Sync="TRUE">0</atprecis><attscale Sync="TRUE">0</attscale></attr><attr xmlns=""><attrlabl>DHSREGNA</attrlabl><attalias>DHS Region Name</attalias><attrdef>name associated with the DHS region created for sampling, this variable will match either v024 or the country specific region variable in the DHS recode file</attrdef><attrdefs>survey documentation</attrdefs><attrtype Sync="TRUE">String</attrtype><attwidth Sync="TRUE">254</attwidth><atprecis Sync="TRUE">0</atprecis><attscale Sync="TRUE">0</attscale></attr><attr xmlns=""><attrlabl>SOURCE</attrlabl><attalias>Coordinate Source</attalias><attrdef>source of data used to determine the latitude and longitude coordinates</attrdef><attrdefs>DHS GIS Team</attrdefs><attrvai><attrvae>“GPS” for data collected by the survey team, "CEN" for preexisting data provided by the census agency/ministry, “GAZ” for data extracted from a gazetteer of village/place names, “MAP” for data extracted from a paper map, "MIS" for clusters in which data could not be fully verified</attrvae></attrvai><attrtype Sync="TRUE">String</attrtype><attwidth Sync="TRUE">254</attwidth><atprecis Sync="TRUE">0</atprecis><attscale Sync="TRUE">0</attscale></attr><attr xmlns=""><attrlabl>URBAN_RURA</attrlabl><attalias>Urban or Rural Classification</attalias><attrdef>cluster's Urban (U) and Rural (R) DHS sample classification</attrdef><attrdefs>survey documentation</attrdefs><attrvai><attrvae>“U” for urban clusters, "R" for rural clusters</attrvae></attrvai><attrtype Sync="TRUE">String</attrtype><attwidth Sync="TRUE">254</attwidth><atprecis Sync="TRUE">0</atprecis><attscale Sync="TRUE">0</attscale></attr><attr xmlns=""><attrlabl>LATNUM</attrlabl><attalias>Latitude</attalias><attrdef>cluster's latitude coordinate in decimal degrees</attrdef><attrdefs>see SOURCE field</attrdefs><attrtype Sync="TRUE">Double</attrtype><attwidth Sync="TRUE">19</attwidth><atprecis Sync="TRUE">0</atprecis><attscale Sync="TRUE">0</attscale></attr><attr xmlns=""><attrlabl>LONGNUM</attrlabl><attalias>Longitude</attalias><attrdef>cluster's longitude coordinate in decimal degrees</attrdef><attrdefs>see SOURCE field</attrdefs><attrtype Sync="TRUE">Double</attrtype><attwidth Sync="TRUE">19</attwidth><atprecis Sync="TRUE">0</atprecis><attscale Sync="TRUE">0</attscale></attr><attr xmlns=""><attrlabl>ALT_GPS</attrlabl><attalias>GPS Altitude</attalias><attrdef>cluster's elevation/altitude (in meters) recorded from the GPS receiver; if this information is not available, this field will be "9999"</attrdef><attrdefs>DHS field GPS receiver</attrdefs><attrtype Sync="TRUE">Double</attrtype><attwidth Sync="TRUE">19</attwidth><atprecis Sync="TRUE">0</atprecis><attscale Sync="TRUE">0</attscale></attr><attr xmlns=""><attrlabl>ALT_DEM</attrlabl><attalias>DEM Altitude</attalias><attrdef>cluster's elevation/altitude (in meters) from the SRTM (Shuttle Radar Topography Mission) DEM (Digital Elevation Model) for the specified coordinate location, elevations are regularly spaced at 30-arc seconds or approximately 1 kilometer; if coordinates are missing, this field will be "9999"</attrdef><attrdefs>http://dds.cr.usgs.gov/srtm/version1/SRTM30</attrdefs><attrtype Sync="TRUE">Double</attrtype><attwidth Sync="TRUE">19</attwidth><atprecis Sync="TRUE">0</atprecis><attscale Sync="TRUE">0</attscale></attr><attr xmlns=""><attrlabl>DATUM</attrlabl><attalias>Datum</attalias><attrdef>coordinate reference system and geographic datum, it is always "WGS84" for the World Geodetic System (WGS) 1984</attrdef><attrdefs>DHS GIS Team</attrdefs><attrtype Sync="TRUE">String</attrtype><attwidth Sync="TRUE">254</attwidth><atprecis Sync="TRUE">0</atprecis><attscale Sync="TRUE">0</attscale></attr></detailed></eainfo><dqInfo xmlns=""><dqScope><scpLvl><ScopeCd value="001"/></scpLvl></dqScope><dataLineage><dataSource xmlns="" type=""><srcRefSys xmlns=""><identCode code="WGS84"/><identAuth xmlns=""><citId xmlns=""><identCode>KEGE43FL</identCode></citId></identAuth></srcRefSys></dataSource></dataLineage></dqInfo><mdHrLv><ScopeCd value="005"/></mdHrLv><mdMaint xmlns=""><maintFreq><MaintFreqCd value="011"/></maintFreq><maintScp><ScopeCd value="001"/></maintScp><dateNext>20110502</dateNext></mdMaint><mdDateSt>20110502</mdDateSt><mdLang><languageCode value="eng" Sync="TRUE"/><countryCode value="USA" Sync="TRUE"/></mdLang><distInfo><distFormat><formatName Sync="TRUE">Shapefile</formatName></distFormat><distTranOps><transSize Sync="TRUE">0.011</transSize></distTranOps></distInfo><mdHrLvName Sync="TRUE">dataset</mdHrLvName><refSysInfo><RefSystem><refSysID><identCode code="0" Sync="TRUE" value="0"/></refSysID></RefSystem></refSysInfo><spatRepInfo><VectSpatRep><geometObjs Name="KEGE43FL"><geoObjTyp><GeoObjTypCd value="004" Sync="TRUE"></GeoObjTypCd></geoObjTyp><geoObjCnt Sync="TRUE">400</geoObjCnt></geometObjs><topLvl><TopoLevCd value="001" Sync="TRUE"></TopoLevCd></topLvl></VectSpatRep></spatRepInfo><spdoinfo><ptvctinf><esriterm><efeatyp Sync="TRUE">Simple</efeatyp><efeageom code="1" Sync="TRUE"></efeageom><esritopo Sync="TRUE">FALSE</esritopo><efeacnt Sync="TRUE">400</efeacnt><spindex Sync="TRUE">TRUE</spindex><linrefer Sync="TRUE">FALSE</linrefer></esriterm></ptvctinf></spdoinfo><Binary><Thumbnail><Data EsriPropertyType="PictureX">/9j/4AAQSkZJRgABAQEAAQABAAD/2wBDAAgGBgcGBQgHBwcJCQgKDBQNDAsLDBkSEw8UHRofHh0a
HBwgJC4nICIsIxwcKDcpLDAxNDQ0Hyc5PTgyPC4zNDL/2wBDAQkJCQwLDBgNDRgyIRwhMjIyMjIy
MjIyMjIyMjIyMjIyMjIyMjIyMjIyMjIyMjIyMjIyMjIyMjIyMjIyMjIyMjL/wAARCACFAMgDASIA
AhEBAxEB/8QAHwAAAQUBAQEBAQEAAAAAAAAAAAECAwQFBgcICQoL/8QAtRAAAgEDAwIEAwUFBAQA
AAF9AQIDAAQRBRIhMUEGE1FhByJxFDKBkaEII0KxwRVS0fAkM2JyggkKFhcYGRolJicoKSo0NTY3
ODk6Q0RFRkdISUpTVFVWV1hZWmNkZWZnaGlqc3R1dnd4eXqDhIWGh4iJipKTlJWWl5iZmqKjpKWm
p6ipqrKztLW2t7i5usLDxMXGx8jJytLT1NXW19jZ2uHi4+Tl5ufo6erx8vP09fb3+Pn6/8QAHwEA
AwEBAQEBAQEBAQAAAAAAAAECAwQFBgcICQoL/8QAtREAAgECBAQDBAcFBAQAAQJ3AAECAxEEBSEx
BhJBUQdhcRMiMoEIFEKRobHBCSMzUvAVYnLRChYkNOEl8RcYGRomJygpKjU2Nzg5OkNERUZHSElK
U1RVVldYWVpjZGVmZ2hpanN0dXZ3eHl6goOEhYaHiImKkpOUlZaXmJmaoqOkpaanqKmqsrO0tba3
uLm6wsPExcbHyMnK0tPU1dbX2Nna4uPk5ebn6Onq8vP09fb3+Pn6/9oADAMBAAIRAxEAPwD3+iii
gAooooAKKKKACiiigAooooAKKKKACiiigAooooAKKqX9+unpAzW9zN506QgW8RkKljjc2Oijue1W
6ACiiigAooooAKKKKACiiigAooooAKKKKACiiigAqtqNkuo6dcWTTzwLPGYzLbyGORMjqrDoferN
FADUQRxqgLEKAMsck/U96b58JuDbiWPzwgcx7huCk4Bx1xkEZ9qkqAWVqL5r4W0Qu2jERn2DeUBy
F3dcZ5xQBPRUF7dx2FjcXkqyNHBG0jCNC7EAZOFHJPsKfBMtxbxToHCSIHUOhVgCM8g8g+x5oAko
oooAKaHQyGMMpdQGK55AOcHH4H8jVa2trqG+vJpr554JmUwwGNVEAC4IBHLZPPPSojHpNrrolItI
tVvYtgJKiWZI+cDuQN1AEupajbaRp09/eOyW8C7nZY2cgdOigk0lpYJaz3ky3F1J9rkEpWaUssfy
hdqA/dHGcepNXCQASTgCigDE0Pwzb6Fcz3Ed/qd3JNHHGTe3bTBQgOMA8A8kk1t0UUAFFFFABRRR
QAUUUUAFFFFABRRRQAUUUUAFFFFABRVK4vJ4dUsrVLMyQTiTzLjzVURFQCo2k5bPPTpirpAIwRkG
gABBGQcg0VV03TbPSNPhsLCBYLWEbY41zhRnPf61aoAqaldzWNi09vYz30gZQIICodgWAJG4gcA5
69qt0UUAFY2neHobDXNU1Qymd72ZZUWRQfs58tUYK3XDbFz06CtmuQ8Sxazp/htdviVrfN8DcXv2
IPKkDuQqRqgI3Dci7iD3NAHTahYWuq6fcWF9Cs1rcRmOWNs4ZTwRxU6IscaoihUUAKB2Apw4AGc+
9FABRRRQAUUUUAFFFFABRRRQAUUUUAFFFFABRRRQAVzeueO/D3hu9W11W8kgclAX+zyNGu8Pty4X
HPlsMZzxT/HGoXumeDtQudOura0vMLHDcXMixxxM7hQxLAjjOeRzXy5r+t3iam9ld3K6hYyrLFJB
C5t7f7QzlncAgcCTkMeu0cgAqAD37wD4s/4To3l5q2h7LrRbqVba9S3O3DAj5ASzB9vVRnqPXFdd
4cubZtF0+KO/url5LcTIb/5bl0J+86kA8ZAzj0rxnTvD2n2trpbaQs1xb21pZXGtafpmpyefK7KW
3NEu4MM+WRtIP0HI9g0nS0fUl13UbWGHX5bNYJkjuGlWKMMxATIGAScngcj2yQDerM1DUb221jS7
K10uW5humf7RdBwqWyKucn1JJAA+vpVW31m20yYadq2uWlxqEl15aIiBGXzCzRIVBODtBAJxnHvV
mXX9P/4R261u0ure5s4IpZPNWX92fLzuG4A45UjODQBqUVkeHvENj4g0S31G3ubR9+1JRBOJVjlw
Mx7h1IJH149a16AKmo6la6VbLcXbusbSpCCkbOdzsFUYUE9SOat01HSQEoysASDg5wR1FOoAqacd
Qa2Y6klsk/mvtFuzMvl7jszkA7tuM9s5q3VQXrHVnsPsdyFWATfaio8oksRsBzndxnGOhq3QAUUU
UAFFFFABRRRQAUUUUAFFFFABRRRQAUUUUAU9V0231nSbvTbpQ0FzE0T5UNgEdcEEZHUZHUV4T4ob
wUPBeqf25BHfataOLCDULWGSJpirPs/eeXsD/JJuwCDjGT1Hu+qLqD6ZcLpUltHflf3L3Klow3+0
AQa8M8eeH9U8Q67cWqafINWezRC7yRKl/LGyIzxwyFikYErMGUjPzd+QAT+HdT1PXfFjXfg+NNL2
6cttbW8k8c1uyRSHmZI8eVv27QRkjDcYII7XxX4OWfw9ZyNq8EHiZRHaQ61dymKQliQVBj27jh32
jHJxn1p2mfCmw0OTTpdJ1O7tprM797qkvmSMV8xzuBILIGTGcDdkDPJ2L1bnxLcaVcWVvZy6ba3z
/aodStZEkDRthZIiRwyspxkYIPUUAYmkHXbPXPEGk3uq2g1ueOKXTZ5LQeXJCi7SQA292GTuBJAL
cZGa4fw/8afDsNvrGmavo15HFcXM8ggAa5BDYLKyuRjJLnaAAB78ne+MviTxL4OutP1jSJZPskkZ
gkDQpJCrZzhsruXcD1Dc+WOO9eb/AA21S18Ea4Ne1zTLi3stSjc2CJYiT5CVLusjNvCop54ORmgD
pvh14WvtIms9U1q3u4NHdG1OdbhYmsoQAXiZcyF0deDuxnkg8ZNe9wTRXMEc8EiyQyqHR0OQykZB
B7gioEvrC7neyS5t5ZvKWR4A4LbGzglfQ4P5VbAAGAMAUAVbTT7PTI5xZWkcImleeRYlC+ZI3LMf
Un1NVvD+sjXtHjv/ALDd2Lszo9vdx7JI2VipB7HkdRWnRQAUUVUsL1r5J2azubXyp3hAuFALhTje
uCcqexoAt0UUUAFFFFABRRRQAUUUUAFFFFABRRRQAUUUUAFU9R0mw1aKOO/tY51jkWRN4+6ysGBB
/wB5VOO+OauUUAFFFFAGR4l8Nad4s0d9K1VZntHdXZYpWj3FTkZweR7H2PUCuJfw34c8La/pdu2k
yxWGkaZPLZ3as7vJK5PmJjb80hUFlAOeWwMYx6bUFxZWt40DXNtFMYJBLEZEDeW4yAy56Hk80AeY
XGl6RczTDSLTXpdT0ZrLUZr2eF5ZLoxp8sOJGUs5jY8AAAn14r1RGLxqxVlJAO1uo9jXNXWt6/Ba
3kk+k2Wnpbr5gu7y+Bt9glKncQNykxjf0wCQD0rplZXRXRgysMgg5BFAC1U060msrZop76e8cyvI
JJgoIDMSF+UAYAOB9Kt1BezTW9jcTW9s1zPHGzRwKwUyMBwuTwMnjJoAjhu5pdSurV7GeKGFUKXL
FdkxbOQuDn5cc5A61bqg0uqSS6c8VvbxwOCb1JpCZI/l4CbcqTu4POMdKv0AFFFFABRRRQAUUUUA
FFFFABRRRQAUUUUAFFFFABRRRQAUUUUAFFFFAEc0EVzBJBPEksMilXjdQysD1BB6io7a9tLppo7W
5hlMEhilWNw3luMZU46EZHHvVisfTfCuhaPem807TILa4YSAyRggkO+9vzIH0xgccUAbFcz4x1n+
whot2bi5VJNTitmggKDzvMymCGBJAzuwvPH4i54t1qXw94ZvNViWJmtgrEShyCu4BuFBOcZx79eM
1zPhPSNF13xNqfiyHUrPWF+0n7GYkfFqxjQN95iCxURjIAxg4xkigD0CiiigAooooAKKKKACiiig
AooooAKKKKACiiigAooooAKKKKACiiigAooooAKKKKAOG1+1s2TSdO1/Wob77LeLdTRtCwuHLuVg
ZRCQUCuwXdgg47V02gaBpvhnR4NK0m2WC1hHCjksT1Zj3J9av+RCLg3Aij88oEMm0bioOQM9cZJO
PepKACiiigAooooAKKKKACiiigAooooAKKKKACiiigAooooAKKKKACiiigAooooAKKKKACiiigAo
oooAKKKKACiiigAooooAKKKKAP/Z</Data></Thumbnail></Binary></metadata>
